florgon_cc_cli/commands/__init__.py
florgon_cc_cli/commands/config.py
florgon_cc_cli/commands/host.py
florgon_cc_cli/commands/login.py
florgon_cc_cli/commands/logout.py
florgon_cc_cli/commands/paste.py
florgon_cc_cli/commands/url.py
florgon_cc_cli/config.py
florgon_cc_cli/main.py
florgon_cc_cli/models/error.py
florgon_cc_cli/models/paste.py
florgon_cc_cli/models/stats.py
florgon_cc_cli/models/url.py
florgon_cc_cli/requirements.txt
florgon_cc_cli/services/api.py
florgon_cc_cli/services/config.py
florgon_cc_cli/services/files.py
florgon_cc_cli/services/oauth.py
florgon_cc_cli/services/paste/requests.py
florgon_cc_cli/services/paste/syntax_highlighting.py
florgon_cc_cli/services/url.py
florgon_cc_cli-0.12.0.dist-info/LICENSE
florgon_cc_cli-0.12.0.dist-info/METADATA
florgon_cc_cli-0.12.0.dist-info/WHEEL
florgon_cc_cli-0.12.0.dist-info/entry_points.txt
florgon_cc_cli-0.12.0.dist-info/RECORD
