Metadata-Version: 2.1
Name: florgon-cc-cli
Version: 0.12.0
Summary: CLI interface for https://cc.florgon.com/
Home-page: https://cc.florgon.com/
License: MIT
Keywords: cli,url shortener,paste manager
Author: Степан Зубков
Author-email: zubkovbackend@gmail.com
Requires-Python: >=3.7,<4.0
Classifier: Development Status :: 3 - Alpha
Classifier: Environment :: Console
Classifier: Intended Audience :: End Users/Desktop
Classifier: License :: OSI Approved :: MIT License
Classifier: Programming Language :: Python :: 3
Classifier: Programming Language :: Python :: 3.7
Classifier: Programming Language :: Python :: 3.8
Classifier: Programming Language :: Python :: 3.9
Classifier: Programming Language :: Python :: 3.10
Classifier: Programming Language :: Python :: 3.11
Classifier: Topic :: Utilities
Classifier: Typing :: Typed
Requires-Dist: click (>=8.1.3,<9.0.0)
Requires-Dist: pick (>=2.2.0,<3.0.0)
Requires-Dist: pygments (>=2.15.1,<3.0.0)
Requires-Dist: requests (>=2.28.2,<3.0.0)
Requires-Dist: toml (>=0.10.2,<0.11.0)
